{
    "id": 1317,
    "name": "Necrophagist Mage",
    "name_ru": "Пожиратель Маг",
    "class_id": 30,
    "class_2_id": 0,
    "race_id": 28,
    "alliance_id": 25,
    "alliance_2_id": 0,
    "rarity_id": 7,
    "cost_gold": "1.0Е+1325",
    "buy_level": 6500,
    "image": "images/heroes/1317.webp",
    "power": 630,
    "base_damage": "2Е+1316",
    "hp": 107,
    "hp_main": 0,
    "atk": 82,
    "atk_main": 0,
    "def": 82,
    "def_main": 0,
    "wis": 167,
    "wis_main": 1,
    "agi": 104,
    "agi_main": 0,
    "bonus_event": 10,
    "bonus_siege": 0,
    "bonus_lair": 0,
    "shards": 2250,
    "order": 302,
    "color_1": "#000000",
    "color_2": "#000000",
    "is_active": 1,
    "skills": [
        {
            "id": 2676,
            "hero_id": 1317,
            "boss_id": null,
            "guard_id": null,
            "image": "images/skills/1317_2676.webp",
            "image_id": 3480,
            "type": "active",
            "chance": 30,
            "created": "2023-10-12 12:27:50",
            "updated": "2024-06-18 13:58:33",
            "status": null,
            "name": "Deals massive WIS-based damage to 4 random enemies with a power of 100% ",
            "name_ru": "Наносит мощный урон WIS по 4 случайным соперникам силой 100%"
        }
    ],
    "alliance_data": {
        "id": 25,
        "name": "Wanderers",
        "color": "#add4d0",
        "name_ru": "Странники",
        "image": "images/gallery/assets/images/categories/alliances/1d98a3971db2e88ebd82b71ebe768f06.png",
        "items": [
            {
                "id": 91,
                "alliance_id": 25,
                "min": 3,
                "description": "All wanderers receive a 30% bonus to defend against magical attacks. Additionally, the wanderer can attack an enemy.",
                "ru_description": "Все странники получают бонус 30% к защите от магических атак. Странник дополнительно атакует врага.",
                "created": "2023-06-21 14:51:36",
                "updated": "2023-06-21 14:53:36"
            }
        ]
    },
    "cat": "2",
    "index_in_category": 83
}