{
    "id": 240,
    "name": "Ah-Puch",
    "name_ru": "Ах-Пуч",
    "class_id": 20,
    "class_2_id": 0,
    "race_id": 30,
    "alliance_id": 12,
    "alliance_2_id": 0,
    "rarity_id": 7,
    "cost_gold": "1.0E+974",
    "buy_level": 4666,
    "image": "images/heroes/240.webp",
    "power": 645,
    "base_damage": "5.1Е+963",
    "hp": 135,
    "hp_main": 0,
    "atk": 100,
    "atk_main": 0,
    "def": 131,
    "def_main": 0,
    "wis": 137,
    "wis_main": 1,
    "agi": 125,
    "agi_main": 0,
    "bonus_event": 10,
    "bonus_siege": 0,
    "bonus_lair": 0,
    "shards": 2000,
    "order": 289,
    "color_1": "#000000",
    "color_2": "#000000",
    "is_active": 1,
    "skills": [
        {
            "id": 4118,
            "hero_id": 240,
            "boss_id": null,
            "guard_id": null,
            "image": "images/skills/240_4118.webp",
            "image_id": 3446,
            "type": "reactive",
            "chance": 75,
            "created": "2024-04-03 16:26:26",
            "updated": "2024-06-18 13:58:33",
            "status": null,
            "name": "Revives and fully restores HP of 1 allies.",
            "name_ru": "Воскрешает и восстанавливает полностью HP 1 союзников."
        }
    ],
    "alliance_data": {
        "id": 12,
        "name": "Sages",
        "color": "#ff8255",
        "name_ru": "Мудрецы",
        "image": "images/gallery/assets/images/categories/alliances/94c0e5787de4117eac96eb92b9a73c95.png",
        "items": [
            {
                "id": 70,
                "alliance_id": 12,
                "min": 2,
                "description": "All heroes receive a 40% bonus to defence against magical attacks",
                "ru_description": "Все герои получают бонус 40% к защите от магических атак",
                "created": "2023-06-21 14:51:36",
                "updated": "2023-06-21 14:53:36"
            },
            {
                "id": 71,
                "alliance_id": 12,
                "min": 4,
                "description": "All heroes receive an 80% bonus to defence against magical attacks",
                "ru_description": "Все герои получают бонус 80% к защите от магических атак",
                "created": "2023-06-21 14:51:36",
                "updated": "2023-06-21 14:53:36"
            }
        ]
    },
    "cat": "3",
    "index_in_category": 39
}